{
  "update_time": "2026-07-20T18:20:48",
  "items": [
    {
      "title": "《八仙！》观后感：一部完成度很高却又多处露怯的电影",
      "url": "https://www.acfun.cn/v/ac48706640",
      "last_hot_value": "3307",
      "first_seen_at": "2026-07-19T21:24:16",
      "last_seen_at": "2026-07-20T18:20:48",
      "consecutive_count": 2,
      "peak_rank": 1,
      "is_new": false
    },
    {
      "title": "特厨探店|小又隐蔽，凭什么能开十多年？小李私藏—三秦人家",
      "url": "https://www.acfun.cn/v/ac48704918",
      "last_hot_value": "4531",
      "first_seen_at": "2026-07-19T12:09:14",
      "last_seen_at": "2026-07-19T21:24:16",
      "consecutive_count": 0,
      "peak_rank": 1,
      "is_new": false
    },
    {
      "title": "《妈妈酱，还养吗？不养门开开》",
      "url": "https://www.acfun.cn/v/ac48701723",
      "last_hot_value": "3087",
      "first_seen_at": "2026-07-18T18:32:38",
      "last_seen_at": "2026-07-19T08:34:30",
      "consecutive_count": 0,
      "peak_rank": 1,
      "is_new": false
    },
    {
      "title": "《动物迷惑行为大赏316》",
      "url": "https://www.acfun.cn/v/ac48706417",
      "last_hot_value": "2450",
      "first_seen_at": "2026-07-20T18:20:48",
      "last_seen_at": "2026-07-20T18:20:48",
      "consecutive_count": 1,
      "peak_rank": 2,
      "is_new": true
    },
    {
      "title": "想我就打给我！★手机竖屏1946★",
      "url": "https://www.acfun.cn/v/ac48704435",
      "last_hot_value": "5419",
      "first_seen_at": "2026-07-19T12:09:14",
      "last_seen_at": "2026-07-19T21:24:16",
      "consecutive_count": 0,
      "peak_rank": 2,
      "is_new": false
    },
    {
      "title": "粉色西服库存-1",
      "url": "https://www.acfun.cn/v/ac48704595",
      "last_hot_value": "3325",
      "first_seen_at": "2026-07-18T22:08:44",
      "last_seen_at": "2026-07-19T15:40:01",
      "consecutive_count": 0,
      "peak_rank": 2,
      "is_new": false
    },
    {
      "title": "这真的不是游戏音乐么",
      "url": "https://www.acfun.cn/v/ac48688068",
      "last_hot_value": "2917",
      "first_seen_at": "2026-07-18T18:32:38",
      "last_seen_at": "2026-07-19T08:34:30",
      "consecutive_count": 0,
      "peak_rank": 2,
      "is_new": false
    },
    {
      "title": "被美国制裁三年的中国芯片公司上市了",
      "url": "https://www.acfun.cn/v/ac48702489",
      "last_hot_value": "2749",
      "first_seen_at": "2026-07-18T03:22:04",
      "last_seen_at": "2026-07-18T19:46:31",
      "consecutive_count": 0,
      "peak_rank": 2,
      "is_new": false
    },
    {
      "title": "这个也是真心喜欢！★手机竖屏1947★",
      "url": "https://www.acfun.cn/v/ac48706859",
      "last_hot_value": "3999",
      "first_seen_at": "2026-07-20T18:20:48",
      "last_seen_at": "2026-07-20T18:20:48",
      "consecutive_count": 1,
      "peak_rank": 3,
      "is_new": true
    },
    {
      "title": "网络上常见的热门短视频集锦 第三千三百一十四期",
      "url": "https://www.acfun.cn/v/ac48705608",
      "last_hot_value": "4230",
      "first_seen_at": "2026-07-19T21:24:16",
      "last_seen_at": "2026-07-19T21:24:16",
      "consecutive_count": 0,
      "peak_rank": 3,
      "is_new": false
    },
    {
      "title": "【东方】推特东方小视频选集 第265期",
      "url": "https://www.acfun.cn/v/ac48703713",
      "last_hot_value": "1353",
      "first_seen_at": "2026-07-18T22:08:44",
      "last_seen_at": "2026-07-19T15:40:01",
      "consecutive_count": 0,
      "peak_rank": 3,
      "is_new": false
    },
    {
      "title": "网络上常见的热门短视频集锦 第三千三百一十一期",
      "url": "https://www.acfun.cn/v/ac48702118",
      "last_hot_value": "4252",
      "first_seen_at": "2026-07-18T18:32:38",
      "last_seen_at": "2026-07-19T08:34:30",
      "consecutive_count": 0,
      "peak_rank": 3,
      "is_new": false
    },
    {
      "title": "女仆来袭！！！猎空舞",
      "url": "https://www.acfun.cn/v/ac48708159",
      "last_hot_value": "1744",
      "first_seen_at": "2026-07-20T18:20:48",
      "last_seen_at": "2026-07-20T18:20:48",
      "consecutive_count": 1,
      "peak_rank": 4,
      "is_new": true
    },
    {
      "title": "索尼为何放弃实体游戏？【老弦外传】",
      "url": "https://www.acfun.cn/v/ac48705089",
      "last_hot_value": "1330",
      "first_seen_at": "2026-07-19T12:09:14",
      "last_seen_at": "2026-07-19T21:24:16",
      "consecutive_count": 0,
      "peak_rank": 4,
      "is_new": false
    },
    {
      "title": "申请加入游戏！欢乐八点档-1714",
      "url": "https://www.acfun.cn/v/ac48704567",
      "last_hot_value": "4874",
      "first_seen_at": "2026-07-18T22:08:44",
      "last_seen_at": "2026-07-19T15:40:01",
      "consecutive_count": 0,
      "peak_rank": 4,
      "is_new": false
    },
    {
      "title": "衣服已经帮你叠好了 你什么时候来拿",
      "url": "https://www.acfun.cn/v/ac48702529",
      "last_hot_value": "2924",
      "first_seen_at": "2026-07-18T18:32:38",
      "last_seen_at": "2026-07-18T19:46:31",
      "consecutive_count": 0,
      "peak_rank": 4,
      "is_new": false
    },
    {
      "title": "网络上常见的热门短视频集锦 第三千三百一十五期",
      "url": "https://www.acfun.cn/v/ac48706864",
      "last_hot_value": "3092",
      "first_seen_at": "2026-07-20T18:20:48",
      "last_seen_at": "2026-07-20T18:20:48",
      "consecutive_count": 1,
      "peak_rank": 5,
      "is_new": true
    },
    {
      "title": "这是懂卖门的！欢乐八点档-1715",
      "url": "https://www.acfun.cn/v/ac48706080",
      "last_hot_value": "2885",
      "first_seen_at": "2026-07-19T21:24:16",
      "last_seen_at": "2026-07-19T21:24:16",
      "consecutive_count": 0,
      "peak_rank": 5,
      "is_new": false
    },
    {
      "title": "当代年轻人精神状态",
      "url": "https://www.acfun.cn/v/ac48704305",
      "last_hot_value": "2362",
      "first_seen_at": "2026-07-18T22:08:44",
      "last_seen_at": "2026-07-19T15:40:01",
      "consecutive_count": 0,
      "peak_rank": 5,
      "is_new": false
    },
    {
      "title": "哪位拉拉人能拒绝突然听上一段冬予呢",
      "url": "https://www.acfun.cn/v/ac48706712",
      "last_hot_value": "1398",
      "first_seen_at": "2026-07-20T18:20:48",
      "last_seen_at": "2026-07-20T18:20:48",
      "consecutive_count": 1,
      "peak_rank": 6,
      "is_new": true
    },
    {
      "title": "网络上常见的热门短视频集锦 第三千三百一十三期",
      "url": "https://www.acfun.cn/v/ac48704440",
      "last_hot_value": "4211",
      "first_seen_at": "2026-07-19T21:24:16",
      "last_seen_at": "2026-07-19T21:24:16",
      "consecutive_count": 0,
      "peak_rank": 6,
      "is_new": false
    },
    {
      "title": "你们喜欢哪一套？★手机竖屏1945★",
      "url": "https://www.acfun.cn/v/ac48702114",
      "last_hot_value": "4527",
      "first_seen_at": "2026-07-18T18:32:38",
      "last_seen_at": "2026-07-19T08:34:30",
      "consecutive_count": 0,
      "peak_rank": 6,
      "is_new": false
    },
    {
      "title": "【DAY2】MyGO!!!!! 9th LIVE「つなぎ目の向こうに」 DAY2",
      "url": "https://www.acfun.cn/v/ac48706657",
      "last_hot_value": "1876",
      "first_seen_at": "2026-07-20T18:20:48",
      "last_seen_at": "2026-07-20T18:20:48",
      "consecutive_count": 1,
      "peak_rank": 7,
      "is_new": true
    },
    {
      "title": "摩多摩多~白丝露腰",
      "url": "https://www.acfun.cn/v/ac48706137",
      "last_hot_value": "1738",
      "first_seen_at": "2026-07-19T21:24:16",
      "last_seen_at": "2026-07-19T21:24:16",
      "consecutive_count": 0,
      "peak_rank": 7,
      "is_new": false
    },
    {
      "title": "正常穿搭无不良影响",
      "url": "https://www.acfun.cn/v/ac48704219",
      "last_hot_value": "2156",
      "first_seen_at": "2026-07-19T12:09:14",
      "last_seen_at": "2026-07-19T15:40:01",
      "consecutive_count": 0,
      "peak_rank": 7,
      "is_new": false
    },
    {
      "title": "谁懂啊，鸣潮演唱会夯爆了",
      "url": "https://www.acfun.cn/v/ac48702733",
      "last_hot_value": "2242",
      "first_seen_at": "2026-07-18T18:32:38",
      "last_seen_at": "2026-07-19T08:34:30",
      "consecutive_count": 0,
      "peak_rank": 7,
      "is_new": false
    },
    {
      "title": "双刀一护真有皮肤！女团即将登录刀鸣！？",
      "url": "https://www.acfun.cn/v/ac48706915",
      "last_hot_value": "1669",
      "first_seen_at": "2026-07-20T18:20:48",
      "last_seen_at": "2026-07-20T18:20:48",
      "consecutive_count": 1,
      "peak_rank": 8,
      "is_new": true
    },
    {
      "title": "统统都带走吧！️",
      "url": "https://www.acfun.cn/v/ac48704926",
      "last_hot_value": "1558",
      "first_seen_at": "2026-07-19T21:24:16",
      "last_seen_at": "2026-07-19T21:24:16",
      "consecutive_count": 0,
      "peak_rank": 8,
      "is_new": false
    },
    {
      "title": "【DAY1】MyGO!!!!! 9th LIVE「つなぎ目の向こうに」 DAY1",
      "url": "https://www.acfun.cn/v/ac48704751",
      "last_hot_value": "1750",
      "first_seen_at": "2026-07-19T12:09:14",
      "last_seen_at": "2026-07-19T15:40:01",
      "consecutive_count": 0,
      "peak_rank": 8,
      "is_new": false
    },
    {
      "title": "【莉莉子】Phut hon 瑜伽裤大摆锤【定制预览】",
      "url": "https://www.acfun.cn/v/ac48699552",
      "last_hot_value": "1539",
      "first_seen_at": "2026-07-18T03:22:04",
      "last_seen_at": "2026-07-18T05:40:59",
      "consecutive_count": 0,
      "peak_rank": 8,
      "is_new": false
    },
    {
      "title": "网络上常见的热门短视频集锦 第三千三百一十六期",
      "url": "https://www.acfun.cn/v/ac48707889",
      "last_hot_value": "2500",
      "first_seen_at": "2026-07-20T18:20:48",
      "last_seen_at": "2026-07-20T18:20:48",
      "consecutive_count": 1,
      "peak_rank": 9,
      "is_new": true
    },
    {
      "title": "摸摸 我的小肚肚～",
      "url": "https://www.acfun.cn/v/ac48704881",
      "last_hot_value": "3009",
      "first_seen_at": "2026-07-19T12:09:14",
      "last_seen_at": "2026-07-19T15:40:01",
      "consecutive_count": 0,
      "peak_rank": 9,
      "is_new": false
    },
    {
      "title": "网络上常见的热门短视频集锦 第三千三百一十二期",
      "url": "https://www.acfun.cn/v/ac48703173",
      "last_hot_value": "4180",
      "first_seen_at": "2026-07-18T18:32:38",
      "last_seen_at": "2026-07-19T08:34:30",
      "consecutive_count": 0,
      "peak_rank": 9,
      "is_new": false
    },
    {
      "title": "在“东吴”面馆，吃了一碗和八年前一样的，鸡汁大排干拌面",
      "url": "https://www.acfun.cn/v/ac48700816",
      "last_hot_value": "1501",
      "first_seen_at": "2026-07-18T03:22:04",
      "last_seen_at": "2026-07-18T05:40:59",
      "consecutive_count": 0,
      "peak_rank": 9,
      "is_new": false
    },
    {
      "title": "【奈²】夏天又来啦",
      "url": "https://www.acfun.cn/v/ac48707910",
      "last_hot_value": "1205",
      "first_seen_at": "2026-07-20T18:20:48",
      "last_seen_at": "2026-07-20T18:20:48",
      "consecutive_count": 1,
      "peak_rank": 10,
      "is_new": true
    },
    {
      "title": "dva赛车服自设~",
      "url": "https://www.acfun.cn/v/ac48706515",
      "last_hot_value": "1380",
      "first_seen_at": "2026-07-19T21:24:16",
      "last_seen_at": "2026-07-19T21:24:16",
      "consecutive_count": 0,
      "peak_rank": 10,
      "is_new": false
    },
    {
      "title": "【东方】ロキ - Ver. HIMEHINA 【铃仙&帝 Ver. MMD】",
      "url": "https://www.acfun.cn/v/ac48699731",
      "last_hot_value": "1111",
      "first_seen_at": "2026-07-18T18:32:38",
      "last_seen_at": "2026-07-18T19:46:31",
      "consecutive_count": 0,
      "peak_rank": 10,
      "is_new": false
    },
    {
      "title": "挑战：竹篮打水…",
      "url": "https://www.acfun.cn/v/ac48700843",
      "last_hot_value": "1554",
      "first_seen_at": "2026-07-18T03:22:04",
      "last_seen_at": "2026-07-18T05:40:59",
      "consecutive_count": 0,
      "peak_rank": 10,
      "is_new": false
    }
  ]
}