{
  "update_time": "2026-07-10T09:25:15",
  "items": [
    {
      "title": "我的梦幻九宫格成绩",
      "url": "https://bbs.hupu.com/search?q=%E6%88%91%E7%9A%84%E6%A2%A6%E5%B9%BB%E4%B9%9D%E5%AE%AB%E6%A0%BC%E6%88%90%E7%BB%A9&topicId=&sortby=general&page=1",
      "last_hot_value": "8715284",
      "first_seen_at": "2026-07-07T13:48:27",
      "last_seen_at": "2026-07-10T09:25:15",
      "consecutive_count": 8,
      "peak_rank": 1,
      "is_new": false
    },
    {
      "title": "埃及 vs 阿根廷",
      "url": "https://bbs.hupu.com/search?q=%E5%9F%83%E5%8F%8A%20vs%20%E9%98%BF%E6%A0%B9%E5%BB%B7&topicId=&sortby=general&page=1",
      "last_hot_value": "8270538",
      "first_seen_at": "2026-07-07T18:20:49",
      "last_seen_at": "2026-07-08T20:01:47",
      "consecutive_count": 0,
      "peak_rank": 1,
      "is_new": false
    },
    {
      "title": "我的82-0赛季阵容",
      "url": "https://bbs.hupu.com/search?q=%E6%88%91%E7%9A%8482-0%E8%B5%9B%E5%AD%A3%E9%98%B5%E5%AE%B9&topicId=&sortby=general&page=1",
      "last_hot_value": "8180460",
      "first_seen_at": "2026-07-10T09:25:15",
      "last_seen_at": "2026-07-10T09:25:15",
      "consecutive_count": 1,
      "peak_rank": 2,
      "is_new": true
    },
    {
      "title": "世界杯完美阵容挑战",
      "url": "https://bbs.hupu.com/search?q=%E4%B8%96%E7%95%8C%E6%9D%AF%E5%AE%8C%E7%BE%8E%E9%98%B5%E5%AE%B9%E6%8C%91%E6%88%98&topicId=&sortby=general&page=1",
      "last_hot_value": "6288515",
      "first_seen_at": "2026-07-10T09:25:15",
      "last_seen_at": "2026-07-10T09:25:15",
      "consecutive_count": 1,
      "peak_rank": 3,
      "is_new": true
    },
    {
      "title": "BLG 3-1力克HLE挺进决赛",
      "url": "https://bbs.hupu.com/search?q=BLG%203-1%E5%8A%9B%E5%85%8BHLE%E6%8C%BA%E8%BF%9B%E5%86%B3%E8%B5%9B&topicId=&sortby=general&page=1",
      "last_hot_value": "1674603",
      "first_seen_at": "2026-07-09T22:59:51",
      "last_seen_at": "2026-07-10T09:25:15",
      "consecutive_count": 2,
      "peak_rank": 4,
      "is_new": false
    },
    {
      "title": "BLG vs HLE",
      "url": "https://bbs.hupu.com/search?q=BLG%20vs%20HLE&topicId=&sortby=general&page=1",
      "last_hot_value": "3194960",
      "first_seen_at": "2026-07-09T22:59:51",
      "last_seen_at": "2026-07-09T22:59:51",
      "consecutive_count": 0,
      "peak_rank": 4,
      "is_new": false
    },
    {
      "title": "T1止步六强刷新队史国际赛事最差成绩",
      "url": "https://bbs.hupu.com/search?q=T1%E6%AD%A2%E6%AD%A5%E5%85%AD%E5%BC%BA%E5%88%B7%E6%96%B0%E9%98%9F%E5%8F%B2%E5%9B%BD%E9%99%85%E8%B5%9B%E4%BA%8B%E6%9C%80%E5%B7%AE%E6%88%90%E7%BB%A9&topicId=&sortby=general&page=1",
      "last_hot_value": "910358",
      "first_seen_at": "2026-07-08T13:02:20",
      "last_seen_at": "2026-07-09T22:59:51",
      "consecutive_count": 0,
      "peak_rank": 4,
      "is_new": false
    },
    {
      "title": "葡萄牙 vs 西班牙",
      "url": "https://bbs.hupu.com/search?q=%E8%91%A1%E8%90%84%E7%89%99%20vs%20%E8%A5%BF%E7%8F%AD%E7%89%99&topicId=&sortby=general&page=1",
      "last_hot_value": "3038040",
      "first_seen_at": "2026-07-07T13:48:27",
      "last_seen_at": "2026-07-07T21:51:31",
      "consecutive_count": 0,
      "peak_rank": 4,
      "is_new": false
    },
    {
      "title": "水浒传之梁山聚义",
      "url": "https://bbs.hupu.com/search?q=%E6%B0%B4%E6%B5%92%E4%BC%A0%E4%B9%8B%E6%A2%81%E5%B1%B1%E8%81%9A%E4%B9%89&topicId=&sortby=general&page=1",
      "last_hot_value": "1078158",
      "first_seen_at": "2026-07-10T09:25:15",
      "last_seen_at": "2026-07-10T09:25:15",
      "consecutive_count": 1,
      "peak_rank": 5,
      "is_new": true
    },
    {
      "title": "G2八千经济翻盘T1挺进下一轮",
      "url": "https://bbs.hupu.com/search?q=G2%E5%85%AB%E5%8D%83%E7%BB%8F%E6%B5%8E%E7%BF%BB%E7%9B%98T1%E6%8C%BA%E8%BF%9B%E4%B8%8B%E4%B8%80%E8%BD%AE&topicId=&sortby=general&page=1",
      "last_hot_value": "1139065",
      "first_seen_at": "2026-07-08T13:02:20",
      "last_seen_at": "2026-07-09T05:20:20",
      "consecutive_count": 0,
      "peak_rank": 5,
      "is_new": false
    },
    {
      "title": "C罗世界杯谢幕",
      "url": "https://bbs.hupu.com/search?q=C%E7%BD%97%E4%B8%96%E7%95%8C%E6%9D%AF%E8%B0%A2%E5%B9%95&topicId=&sortby=general&page=1",
      "last_hot_value": "1680695",
      "first_seen_at": "2026-07-07T13:48:27",
      "last_seen_at": "2026-07-08T20:01:47",
      "consecutive_count": 0,
      "peak_rank": 5,
      "is_new": false
    },
    {
      "title": "库明加希望获得超过2500万美元的年薪",
      "url": "https://bbs.hupu.com/search?q=%E5%BA%93%E6%98%8E%E5%8A%A0%E5%B8%8C%E6%9C%9B%E8%8E%B7%E5%BE%97%E8%B6%85%E8%BF%872500%E4%B8%87%E7%BE%8E%E5%85%83%E7%9A%84%E5%B9%B4%E8%96%AA&topicId=&sortby=general&page=1",
      "last_hot_value": "791513",
      "first_seen_at": "2026-07-10T09:25:15",
      "last_seen_at": "2026-07-10T09:25:15",
      "consecutive_count": 1,
      "peak_rank": 6,
      "is_new": true
    },
    {
      "title": "法国 vs 摩洛哥",
      "url": "https://bbs.hupu.com/search?q=%E6%B3%95%E5%9B%BD%20vs%20%E6%91%A9%E6%B4%9B%E5%93%A5&topicId=&sortby=general&page=1",
      "last_hot_value": "1547241",
      "first_seen_at": "2026-07-09T22:59:51",
      "last_seen_at": "2026-07-09T22:59:51",
      "consecutive_count": 0,
      "peak_rank": 6,
      "is_new": false
    },
    {
      "title": "詹姆斯短期内不会公布自己下赛季的去向",
      "url": "https://bbs.hupu.com/search?q=%E8%A9%B9%E5%A7%86%E6%96%AF%E7%9F%AD%E6%9C%9F%E5%86%85%E4%B8%8D%E4%BC%9A%E5%85%AC%E5%B8%83%E8%87%AA%E5%B7%B1%E4%B8%8B%E8%B5%9B%E5%AD%A3%E7%9A%84%E5%8E%BB%E5%90%91&topicId=&sortby=general&page=1",
      "last_hot_value": "1237542",
      "first_seen_at": "2026-07-09T05:20:20",
      "last_seen_at": "2026-07-09T22:59:51",
      "consecutive_count": 0,
      "peak_rank": 6,
      "is_new": false
    },
    {
      "title": "Knight赛后发文：决赛加油看我表演吧",
      "url": "https://bbs.hupu.com/search?q=Knight%E8%B5%9B%E5%90%8E%E5%8F%91%E6%96%87%EF%BC%9A%E5%86%B3%E8%B5%9B%E5%8A%A0%E6%B2%B9%E7%9C%8B%E6%88%91%E8%A1%A8%E6%BC%94%E5%90%A7&topicId=&sortby=general&page=1",
      "last_hot_value": "760020",
      "first_seen_at": "2026-07-09T22:59:51",
      "last_seen_at": "2026-07-10T09:25:15",
      "consecutive_count": 2,
      "peak_rank": 7,
      "is_new": false
    },
    {
      "title": "库里谈可能与詹姆斯联手",
      "url": "https://bbs.hupu.com/search?q=%E5%BA%93%E9%87%8C%E8%B0%88%E5%8F%AF%E8%83%BD%E4%B8%8E%E8%A9%B9%E5%A7%86%E6%96%AF%E8%81%94%E6%89%8B&topicId=&sortby=general&page=1",
      "last_hot_value": "752818",
      "first_seen_at": "2026-07-09T05:20:20",
      "last_seen_at": "2026-07-09T05:20:20",
      "consecutive_count": 0,
      "peak_rank": 7,
      "is_new": false
    },
    {
      "title": "脉动运动王者状态拉满",
      "url": "https://bbs.hupu.com/search?q=%E8%84%89%E5%8A%A8%E8%BF%90%E5%8A%A8%E7%8E%8B%E8%80%85%E7%8A%B6%E6%80%81%E6%8B%89%E6%BB%A1&topicId=&sortby=general&page=1",
      "last_hot_value": "726826",
      "first_seen_at": "2026-07-07T13:48:27",
      "last_seen_at": "2026-07-10T09:25:15",
      "consecutive_count": 1,
      "peak_rank": 8,
      "is_new": false
    },
    {
      "title": "美国 vs 比利时",
      "url": "https://bbs.hupu.com/search?q=%E7%BE%8E%E5%9B%BD%20vs%20%E6%AF%94%E5%88%A9%E6%97%B6&topicId=&sortby=general&page=1",
      "last_hot_value": "816136",
      "first_seen_at": "2026-07-07T13:48:27",
      "last_seen_at": "2026-07-07T21:51:31",
      "consecutive_count": 0,
      "peak_rank": 8,
      "is_new": false
    },
    {
      "title": "肖华作为NBA总裁，是功大于过还是过大于功？",
      "url": "https://bbs.hupu.com/search?q=%E8%82%96%E5%8D%8E%E4%BD%9C%E4%B8%BANBA%E6%80%BB%E8%A3%81%EF%BC%8C%E6%98%AF%E5%8A%9F%E5%A4%A7%E4%BA%8E%E8%BF%87%E8%BF%98%E6%98%AF%E8%BF%87%E5%A4%A7%E4%BA%8E%E5%8A%9F%EF%BC%9F&topicId=&sortby=general&page=1",
      "last_hot_value": "695175",
      "first_seen_at": "2026-07-10T09:25:15",
      "last_seen_at": "2026-07-10T09:25:15",
      "consecutive_count": 1,
      "peak_rank": 9,
      "is_new": true
    },
    {
      "title": "BLG今年国际赛BO5已经豪取六连胜未尝败绩",
      "url": "https://bbs.hupu.com/search?q=BLG%E4%BB%8A%E5%B9%B4%E5%9B%BD%E9%99%85%E8%B5%9BBO5%E5%B7%B2%E7%BB%8F%E8%B1%AA%E5%8F%96%E5%85%AD%E8%BF%9E%E8%83%9C%E6%9C%AA%E5%B0%9D%E8%B4%A5%E7%BB%A9&topicId=&sortby=general&page=1",
      "last_hot_value": "928487",
      "first_seen_at": "2026-07-09T22:59:51",
      "last_seen_at": "2026-07-09T22:59:51",
      "consecutive_count": 0,
      "peak_rank": 9,
      "is_new": false
    },
    {
      "title": "米切尔4年2.73亿顶薪提前续约骑士",
      "url": "https://bbs.hupu.com/search?q=%E7%B1%B3%E5%88%87%E5%B0%944%E5%B9%B42.73%E4%BA%BF%E9%A1%B6%E8%96%AA%E6%8F%90%E5%89%8D%E7%BB%AD%E7%BA%A6%E9%AA%91%E5%A3%AB&topicId=&sortby=general&page=1",
      "last_hot_value": "792254",
      "first_seen_at": "2026-07-08T13:02:20",
      "last_seen_at": "2026-07-08T20:01:47",
      "consecutive_count": 0,
      "peak_rank": 9,
      "is_new": false
    },
    {
      "title": "杨瀚森尝试用英语接受采访",
      "url": "https://bbs.hupu.com/search?q=%E6%9D%A8%E7%80%9A%E6%A3%AE%E5%B0%9D%E8%AF%95%E7%94%A8%E8%8B%B1%E8%AF%AD%E6%8E%A5%E5%8F%97%E9%87%87%E8%AE%BF&topicId=&sortby=general&page=1",
      "last_hot_value": "644587",
      "first_seen_at": "2026-07-10T09:25:15",
      "last_seen_at": "2026-07-10T09:25:15",
      "consecutive_count": 1,
      "peak_rank": 10,
      "is_new": true
    },
    {
      "title": "詹姆斯提前告知杰弗森去向计划",
      "url": "https://bbs.hupu.com/search?q=%E8%A9%B9%E5%A7%86%E6%96%AF%E6%8F%90%E5%89%8D%E5%91%8A%E7%9F%A5%E6%9D%B0%E5%BC%97%E6%A3%AE%E5%8E%BB%E5%90%91%E8%AE%A1%E5%88%92&topicId=&sortby=general&page=1",
      "last_hot_value": "611414",
      "first_seen_at": "2026-07-09T05:20:20",
      "last_seen_at": "2026-07-09T05:20:20",
      "consecutive_count": 0,
      "peak_rank": 10,
      "is_new": false
    }
  ]
}