{
  "update_time": "2026-06-26T11:19:16",
  "items": [
    {
      "title": "苹果提高 Mac、iPad、Vision Pro、HomePod 等产品价格，以应对内存短缺",
      "url": "https://www.ithome.com/0/968/675.htm",
      "last_hot_value": "",
      "first_seen_at": "2026-06-26T11:19:16",
      "last_seen_at": "2026-06-26T11:19:16",
      "consecutive_count": 1,
      "peak_rank": 1,
      "is_new": true
    },
    {
      "title": "“开屏广告没了”登顶热搜",
      "url": "https://www.ithome.com/0/967/657.htm",
      "last_hot_value": "",
      "first_seen_at": "2026-06-23T23:46:56",
      "last_seen_at": "2026-06-24T11:29:50",
      "consecutive_count": 0,
      "peak_rank": 1,
      "is_new": false
    },
    {
      "title": "阿里管理层集体下田插秧团建，马云、吴泳铭、周靖人等现身",
      "url": "https://www.ithome.com/0/967/258.htm",
      "last_hot_value": "",
      "first_seen_at": "2026-06-23T23:46:56",
      "last_seen_at": "2026-06-23T23:46:56",
      "consecutive_count": 0,
      "peak_rank": 1,
      "is_new": false
    },
    {
      "title": "138.8 万元起，尊界 S800 Grand Design 典藏大观正式发布",
      "url": "https://www.ithome.com/0/968/672.htm",
      "last_hot_value": "",
      "first_seen_at": "2026-06-26T11:19:16",
      "last_seen_at": "2026-06-26T11:19:16",
      "consecutive_count": 1,
      "peak_rank": 2,
      "is_new": true
    },
    {
      "title": "小米首款 NAS：Xiaomi 智能存储官宣，众筹到手价 2299 元起",
      "url": "https://www.ithome.com/0/967/760.htm",
      "last_hot_value": "",
      "first_seen_at": "2026-06-24T11:29:50",
      "last_seen_at": "2026-06-24T11:29:50",
      "consecutive_count": 0,
      "peak_rank": 2,
      "is_new": false
    },
    {
      "title": "金山办公 WPS 回应 C 盘占用问题：已成立专项组核查，优化正在推进",
      "url": "https://www.ithome.com/0/967/361.htm",
      "last_hot_value": "",
      "first_seen_at": "2026-06-23T23:46:56",
      "last_seen_at": "2026-06-23T23:46:56",
      "consecutive_count": 0,
      "peak_rank": 2,
      "is_new": false
    },
    {
      "title": "苹果代工厂塔塔电子被黑，部分 iPhone 18 Pro 与 A20 Pro 资料确认泄露",
      "url": "https://www.ithome.com/0/968/710.htm",
      "last_hot_value": "",
      "first_seen_at": "2026-06-26T11:19:16",
      "last_seen_at": "2026-06-26T11:19:16",
      "consecutive_count": 1,
      "peak_rank": 3,
      "is_new": true
    },
    {
      "title": "豆包正式推出专业版，连续包月 68 元起、最高 500 元",
      "url": "https://www.ithome.com/0/967/743.htm",
      "last_hot_value": "",
      "first_seen_at": "2026-06-24T11:29:50",
      "last_seen_at": "2026-06-24T11:29:50",
      "consecutive_count": 0,
      "peak_rank": 3,
      "is_new": false
    },
    {
      "title": "美团员工发长文《置身团内》谈公司困境：不是没有执行力，而是形成了路径依赖",
      "url": "https://www.ithome.com/0/967/284.htm",
      "last_hot_value": "",
      "first_seen_at": "2026-06-23T23:46:56",
      "last_seen_at": "2026-06-23T23:46:56",
      "consecutive_count": 0,
      "peak_rank": 3,
      "is_new": false
    },
    {
      "title": "半导体行业重大突破！IBM 推出全球首个亚 1 纳米芯片技术",
      "url": "https://www.ithome.com/0/968/648.htm",
      "last_hot_value": "",
      "first_seen_at": "2026-06-26T11:19:16",
      "last_seen_at": "2026-06-26T11:19:16",
      "consecutive_count": 1,
      "peak_rank": 4,
      "is_new": true
    },
    {
      "title": "小米 REDMI K90 至尊版手机官宣 6 月 30 日发布：风冷主动散热、3K 档游戏性能旗舰",
      "url": "https://www.ithome.com/0/967/740.htm",
      "last_hot_value": "",
      "first_seen_at": "2026-06-24T11:29:50",
      "last_seen_at": "2026-06-24T11:29:50",
      "consecutive_count": 0,
      "peak_rank": 4,
      "is_new": false
    },
    {
      "title": "Steam 国区已屏蔽“LGBTQ+”标签搜索，被标记为不当内容",
      "url": "https://www.ithome.com/0/968/703.htm",
      "last_hot_value": "",
      "first_seen_at": "2026-06-26T11:19:16",
      "last_seen_at": "2026-06-26T11:19:16",
      "consecutive_count": 1,
      "peak_rank": 5,
      "is_new": true
    },
    {
      "title": "小米：电池升级服务预计今年第四季度新增小米 14、14 Pro 手机支持",
      "url": "https://www.ithome.com/0/967/773.htm",
      "last_hot_value": "",
      "first_seen_at": "2026-06-24T11:29:50",
      "last_seen_at": "2026-06-24T11:29:50",
      "consecutive_count": 0,
      "peak_rank": 5,
      "is_new": false
    },
    {
      "title": "苹果 iOS 27 Beta 2 更新汇总：洞察支出、升级 AI 写作、增强 RCS 聊天",
      "url": "https://www.ithome.com/0/967/252.htm",
      "last_hot_value": "",
      "first_seen_at": "2026-06-23T23:46:56",
      "last_seen_at": "2026-06-23T23:46:56",
      "consecutive_count": 0,
      "peak_rank": 5,
      "is_new": false
    },
    {
      "title": "鸿蒙智行尊界 V800/V680 亮相，预售价 80 万-120 万 / 65 万-90 万元",
      "url": "https://www.ithome.com/0/968/674.htm",
      "last_hot_value": "",
      "first_seen_at": "2026-06-26T11:19:16",
      "last_seen_at": "2026-06-26T11:19:16",
      "consecutive_count": 1,
      "peak_rank": 6,
      "is_new": true
    },
    {
      "title": "全新理想 L8 正式上市：行业唯一标配 4 零重力座椅，限时 35.98 万-41.98 万元",
      "url": "https://www.ithome.com/0/967/675.htm",
      "last_hot_value": "",
      "first_seen_at": "2026-06-24T11:29:50",
      "last_seen_at": "2026-06-24T11:29:50",
      "consecutive_count": 0,
      "peak_rank": 6,
      "is_new": false
    },
    {
      "title": "小鹏 MONA L03“乌梅子酱”官图公布，系列首款 SUV",
      "url": "https://www.ithome.com/0/967/334.htm",
      "last_hot_value": "",
      "first_seen_at": "2026-06-23T23:46:56",
      "last_seen_at": "2026-06-23T23:46:56",
      "consecutive_count": 0,
      "peak_rank": 6,
      "is_new": false
    },
    {
      "title": "iPad / Mac 等涨价只是开始？苹果声明暗示后续还有新一轮调价",
      "url": "https://www.ithome.com/0/968/736.htm",
      "last_hot_value": "",
      "first_seen_at": "2026-06-26T11:19:16",
      "last_seen_at": "2026-06-26T11:19:16",
      "consecutive_count": 1,
      "peak_rank": 7,
      "is_new": true
    },
    {
      "title": "iQOO 15/15 Ultra 手机新一轮涨价，最高涨 700 元",
      "url": "https://www.ithome.com/0/967/866.htm",
      "last_hot_value": "",
      "first_seen_at": "2026-06-24T11:29:50",
      "last_seen_at": "2026-06-24T11:29:50",
      "consecutive_count": 0,
      "peak_rank": 7,
      "is_new": false
    },
    {
      "title": "小米 REDMI 17C 手机上架：6.88 英寸 120Hz 大屏、5160mAh 电池，799 元起",
      "url": "https://www.ithome.com/0/967/326.htm",
      "last_hot_value": "",
      "first_seen_at": "2026-06-23T23:46:56",
      "last_seen_at": "2026-06-23T23:46:56",
      "consecutive_count": 0,
      "peak_rank": 7,
      "is_new": false
    },
    {
      "title": "Mac 和 iPad 涨价后，古尔曼预测苹果下周开启返校季促销活动",
      "url": "https://www.ithome.com/0/968/725.htm",
      "last_hot_value": "",
      "first_seen_at": "2026-06-26T11:19:16",
      "last_seen_at": "2026-06-26T11:19:16",
      "consecutive_count": 1,
      "peak_rank": 8,
      "is_new": true
    },
    {
      "title": "酷态科 CP 桌面模块风扇发布：有线 / 无线双供电模式，99 元",
      "url": "https://www.ithome.com/0/967/840.htm",
      "last_hot_value": "",
      "first_seen_at": "2026-06-24T11:29:50",
      "last_seen_at": "2026-06-24T11:29:50",
      "consecutive_count": 0,
      "peak_rank": 8,
      "is_new": false
    },
    {
      "title": "Model 3 撞穿民宅致一死，特斯拉高管称驾驶员全程深踩油门",
      "url": "https://www.ithome.com/0/967/254.htm",
      "last_hot_value": "",
      "first_seen_at": "2026-06-23T23:46:56",
      "last_seen_at": "2026-06-23T23:46:56",
      "consecutive_count": 0,
      "peak_rank": 8,
      "is_new": false
    },
    {
      "title": "互删好友后朋友圈痕迹还在吗？微信回应称自己的回复还在，但 TA 的痕迹全部撤走",
      "url": "https://www.ithome.com/0/968/822.htm",
      "last_hot_value": "",
      "first_seen_at": "2026-06-26T11:19:16",
      "last_seen_at": "2026-06-26T11:19:16",
      "consecutive_count": 1,
      "peak_rank": 9,
      "is_new": true
    },
    {
      "title": "天涯社区重启超半月热度消退，创始人邢明回应称习惯了被唱衰、但这次失败概率很低",
      "url": "https://www.ithome.com/0/967/779.htm",
      "last_hot_value": "",
      "first_seen_at": "2026-06-24T11:29:50",
      "last_seen_at": "2026-06-24T11:29:50",
      "consecutive_count": 0,
      "peak_rank": 9,
      "is_new": false
    },
    {
      "title": "SpaceX 股价大跌近 17%，已跌破 IPO 首日收盘价",
      "url": "https://www.ithome.com/0/967/248.htm",
      "last_hot_value": "",
      "first_seen_at": "2026-06-23T23:46:56",
      "last_seen_at": "2026-06-23T23:46:56",
      "consecutive_count": 0,
      "peak_rank": 9,
      "is_new": false
    },
    {
      "title": "鸿蒙智行尊界 V800/V680 预售 1 小时订单量突破 3200 台，预售价 65 万起",
      "url": "https://www.ithome.com/0/968/697.htm",
      "last_hot_value": "",
      "first_seen_at": "2026-06-26T11:19:16",
      "last_seen_at": "2026-06-26T11:19:16",
      "consecutive_count": 1,
      "peak_rank": 10,
      "is_new": true
    },
    {
      "title": "小鹏 MONA L03 设计团队公布：前法拉利设计师胡安马 · 洛佩兹带队",
      "url": "https://www.ithome.com/0/967/752.htm",
      "last_hot_value": "",
      "first_seen_at": "2026-06-24T11:29:50",
      "last_seen_at": "2026-06-24T11:29:50",
      "consecutive_count": 0,
      "peak_rank": 10,
      "is_new": false
    },
    {
      "title": "何小鹏称 MONA 首款 SUV 车型 L03 对标 30 万级开发：价格当然不会超 30 万",
      "url": "https://www.ithome.com/0/967/358.htm",
      "last_hot_value": "",
      "first_seen_at": "2026-06-23T23:46:56",
      "last_seen_at": "2026-06-23T23:46:56",
      "consecutive_count": 0,
      "peak_rank": 10,
      "is_new": false
    }
  ]
}