{
  "update_time": "2026-07-14T21:09:32",
  "items": [
    {
      "title": "安徽省宿州市砀山县气象台发布强对流黄色预警信号",
      "url": "https://www.nmc.cn/publish/alarm/34132141600000_20260715042349.html",
      "last_hot_value": "黄色",
      "first_seen_at": "2026-07-14T21:09:32",
      "last_seen_at": "2026-07-14T21:09:32",
      "consecutive_count": 1,
      "peak_rank": 1,
      "is_new": true
    },
    {
      "title": "陕西省汉中市勉县气象台发布雷雨黄色预警信号",
      "url": "http://www.weather.com.cn/alarm/newalarmcontent.shtml?file=101110803-20260714134031-9302.html",
      "last_hot_value": "黄色",
      "first_seen_at": "2026-07-14T05:57:24",
      "last_seen_at": "2026-07-14T05:57:24",
      "consecutive_count": 0,
      "peak_rank": 1,
      "is_new": false
    },
    {
      "title": "河南省濮阳市南乐县气象台发布高温橙色预警信号",
      "url": "https://www.nmc.cn/publish/alarm/41092341600000_20260714110839.html",
      "last_hot_value": "橙色",
      "first_seen_at": "2026-07-14T03:32:11",
      "last_seen_at": "2026-07-14T03:32:11",
      "consecutive_count": 0,
      "peak_rank": 1,
      "is_new": false
    },
    {
      "title": "广西壮族自治区钦州市灵山县气象台发布雷电黄色预警信号",
      "url": "https://www.nmc.cn/publish/alarm/45072141600000_20260714051857.html",
      "last_hot_value": "黄色",
      "first_seen_at": "2026-07-13T21:42:20",
      "last_seen_at": "2026-07-13T21:42:20",
      "consecutive_count": 0,
      "peak_rank": 1,
      "is_new": false
    },
    {
      "title": "江西省上饶市三清山气象台发布大雾黄色预警信号",
      "url": "https://www.nmc.cn/publish/alarm/36112341600000_20260714041553.html",
      "last_hot_value": "黄色",
      "first_seen_at": "2026-07-13T20:30:52",
      "last_seen_at": "2026-07-13T20:30:52",
      "consecutive_count": 0,
      "peak_rank": 1,
      "is_new": false
    },
    {
      "title": "安徽省宣城市泾县气象台发布暴雨黄色预警信号",
      "url": "https://www.nmc.cn/publish/alarm/34182341600000_20260713045241.html",
      "last_hot_value": "黄色",
      "first_seen_at": "2026-07-12T21:19:19",
      "last_seen_at": "2026-07-12T21:19:19",
      "consecutive_count": 0,
      "peak_rank": 1,
      "is_new": false
    },
    {
      "title": "江西省赣州市瑞金市气象台发布雷电黄色预警信号",
      "url": "https://www.nmc.cn/publish/alarm/36078141600000_20260712191918.html",
      "last_hot_value": "黄色",
      "first_seen_at": "2026-07-12T11:55:11",
      "last_seen_at": "2026-07-12T11:55:11",
      "consecutive_count": 0,
      "peak_rank": 1,
      "is_new": false
    },
    {
      "title": "吉林省吉林市永吉县气象台发布大雾黄色预警信号",
      "url": "https://www.nmc.cn/publish/alarm/22022141600000_20260715041956.html",
      "last_hot_value": "黄色",
      "first_seen_at": "2026-07-14T21:09:32",
      "last_seen_at": "2026-07-14T21:09:32",
      "consecutive_count": 1,
      "peak_rank": 2,
      "is_new": true
    },
    {
      "title": "山西省忻州市忻府区气象台发布其他蓝色预警信号",
      "url": "http://www.weather.com.cn/alarm/newalarmcontent.shtml?file=101101016-20260714134000-5201.html",
      "last_hot_value": "蓝色",
      "first_seen_at": "2026-07-14T05:57:24",
      "last_seen_at": "2026-07-14T05:57:24",
      "consecutive_count": 0,
      "peak_rank": 2,
      "is_new": false
    },
    {
      "title": "山西省临汾市水利局与临汾市气象台发布山洪灾害气象风险橙色预警信号",
      "url": "https://www.nmc.cn/publish/alarm/14100041600000_20260714110741.html",
      "last_hot_value": "橙色",
      "first_seen_at": "2026-07-14T03:32:11",
      "last_seen_at": "2026-07-14T03:32:11",
      "consecutive_count": 0,
      "peak_rank": 2,
      "is_new": false
    },
    {
      "title": "贵州省黔南布依族苗族自治州荔波县气象台发布大雾橙色预警信号",
      "url": "https://www.nmc.cn/publish/alarm/52272241600000_20260714051800.html",
      "last_hot_value": "橙色",
      "first_seen_at": "2026-07-13T21:42:20",
      "last_seen_at": "2026-07-13T21:42:20",
      "consecutive_count": 0,
      "peak_rank": 2,
      "is_new": false
    },
    {
      "title": "吉林省四平市伊通满族自治县气象台发布暴雨黄色预警信号",
      "url": "https://www.nmc.cn/publish/alarm/22032341600000_20260714041059.html",
      "last_hot_value": "黄色",
      "first_seen_at": "2026-07-13T20:30:52",
      "last_seen_at": "2026-07-13T20:30:52",
      "consecutive_count": 0,
      "peak_rank": 2,
      "is_new": false
    },
    {
      "title": "辽宁省鞍山市台安县气象台发布暴雨红色预警信号",
      "url": "https://www.nmc.cn/publish/alarm/21032141600000_20260713045000.html",
      "last_hot_value": "红色",
      "first_seen_at": "2026-07-12T21:19:19",
      "last_seen_at": "2026-07-12T21:19:19",
      "consecutive_count": 0,
      "peak_rank": 2,
      "is_new": false
    },
    {
      "title": "贵州省毕节市金沙县气象台发布雷雨强风黄色预警信号",
      "url": "https://www.nmc.cn/publish/alarm/52052341600000_20260712191807.html",
      "last_hot_value": "黄色",
      "first_seen_at": "2026-07-12T11:55:11",
      "last_seen_at": "2026-07-12T11:55:11",
      "consecutive_count": 0,
      "peak_rank": 2,
      "is_new": false
    },
    {
      "title": "四川省雅安市名山区气象台发布雷电黄色预警信号",
      "url": "https://www.nmc.cn/publish/alarm/51180341600000_20260715041807.html",
      "last_hot_value": "黄色",
      "first_seen_at": "2026-07-14T21:09:32",
      "last_seen_at": "2026-07-14T21:09:32",
      "consecutive_count": 1,
      "peak_rank": 3,
      "is_new": true
    },
    {
      "title": "福建省厦门市翔安区气象台发布暴雨黄色预警信号",
      "url": "http://www.weather.com.cn/alarm/newalarmcontent.shtml?file=101230207-20260714133926-0202.html",
      "last_hot_value": "黄色",
      "first_seen_at": "2026-07-14T05:57:24",
      "last_seen_at": "2026-07-14T05:57:24",
      "consecutive_count": 0,
      "peak_rank": 3,
      "is_new": false
    },
    {
      "title": "河北省邯郸市大名县气象台发布暴雨蓝色预警信号",
      "url": "https://www.nmc.cn/publish/alarm/13042541600000_20260714110709.html",
      "last_hot_value": "蓝色",
      "first_seen_at": "2026-07-14T03:32:11",
      "last_seen_at": "2026-07-14T03:32:11",
      "consecutive_count": 0,
      "peak_rank": 3,
      "is_new": false
    },
    {
      "title": "海南省气象台发布海上雷雨大风黄色预警信号",
      "url": "https://www.nmc.cn/publish/alarm/46000041600000_20260714051747.html",
      "last_hot_value": "黄色",
      "first_seen_at": "2026-07-13T21:42:20",
      "last_seen_at": "2026-07-13T21:42:20",
      "consecutive_count": 0,
      "peak_rank": 3,
      "is_new": false
    },
    {
      "title": "陕西省榆林市定边县气象台发布雷雨大风黄色预警信号",
      "url": "https://www.nmc.cn/publish/alarm/61082541600000_20260714040856.html",
      "last_hot_value": "黄色",
      "first_seen_at": "2026-07-13T20:30:52",
      "last_seen_at": "2026-07-13T20:30:52",
      "consecutive_count": 0,
      "peak_rank": 3,
      "is_new": false
    },
    {
      "title": "辽宁省葫芦岛市连山区气象台发布暴雨橙色预警信号",
      "url": "https://www.nmc.cn/publish/alarm/21140241600000_20260713045000.html",
      "last_hot_value": "橙色",
      "first_seen_at": "2026-07-12T21:19:19",
      "last_seen_at": "2026-07-12T21:19:19",
      "consecutive_count": 0,
      "peak_rank": 3,
      "is_new": false
    },
    {
      "title": "河南省洛阳市伊川县气象台发布雷暴大风黄色预警信号",
      "url": "https://www.nmc.cn/publish/alarm/41032941600000_20260712191758.html",
      "last_hot_value": "黄色",
      "first_seen_at": "2026-07-12T11:55:11",
      "last_seen_at": "2026-07-12T11:55:11",
      "consecutive_count": 0,
      "peak_rank": 3,
      "is_new": false
    },
    {
      "title": "广西壮族自治区柳州市融水县气象台发布雷电黄色预警信号",
      "url": "https://www.nmc.cn/publish/alarm/45022541600000_20260715041801.html",
      "last_hot_value": "黄色",
      "first_seen_at": "2026-07-14T21:09:32",
      "last_seen_at": "2026-07-14T21:09:32",
      "consecutive_count": 1,
      "peak_rank": 4,
      "is_new": true
    },
    {
      "title": "江西省萍乡市气象台发布雷电黄色预警信号",
      "url": "http://www.weather.com.cn/alarm/newalarmcontent.shtml?file=1012409-20260714133800-0902.html",
      "last_hot_value": "黄色",
      "first_seen_at": "2026-07-14T05:57:24",
      "last_seen_at": "2026-07-14T05:57:24",
      "consecutive_count": 0,
      "peak_rank": 4,
      "is_new": false
    },
    {
      "title": "山西省临汾市吉县气象台发布暴雨蓝色预警信号",
      "url": "https://www.nmc.cn/publish/alarm/14102841600000_20260714110700.html",
      "last_hot_value": "蓝色",
      "first_seen_at": "2026-07-14T03:32:11",
      "last_seen_at": "2026-07-14T03:32:11",
      "consecutive_count": 0,
      "peak_rank": 4,
      "is_new": false
    },
    {
      "title": "广东省广州市增城区气象台发布雷雨大风黄色预警信号",
      "url": "https://www.nmc.cn/publish/alarm/44011841600000_20260714051741.html",
      "last_hot_value": "黄色",
      "first_seen_at": "2026-07-13T21:42:20",
      "last_seen_at": "2026-07-13T21:42:20",
      "consecutive_count": 0,
      "peak_rank": 4,
      "is_new": false
    },
    {
      "title": "宁夏回族自治区银川市灵武市气象台发布暴雨橙色预警信号",
      "url": "https://www.nmc.cn/publish/alarm/64018141600000_20260714040515.html",
      "last_hot_value": "橙色",
      "first_seen_at": "2026-07-13T20:30:52",
      "last_seen_at": "2026-07-13T20:30:52",
      "consecutive_count": 0,
      "peak_rank": 4,
      "is_new": false
    },
    {
      "title": "湖北省宜昌市五峰土家族自治县气象台发布强对流黄色预警信号",
      "url": "https://www.nmc.cn/publish/alarm/42052941600000_20260713044824.html",
      "last_hot_value": "黄色",
      "first_seen_at": "2026-07-12T21:19:19",
      "last_seen_at": "2026-07-12T21:19:19",
      "consecutive_count": 0,
      "peak_rank": 4,
      "is_new": false
    },
    {
      "title": "贵州省遵义市桐梓县气象台发布雷电黄色预警信号",
      "url": "https://www.nmc.cn/publish/alarm/52032241600000_20260712191722.html",
      "last_hot_value": "黄色",
      "first_seen_at": "2026-07-12T11:55:11",
      "last_seen_at": "2026-07-12T11:55:11",
      "consecutive_count": 0,
      "peak_rank": 4,
      "is_new": false
    },
    {
      "title": "河南省开封市兰考县气象台发布雷暴大风黄色预警信号",
      "url": "https://www.nmc.cn/publish/alarm/41022541600000_20260715041632.html",
      "last_hot_value": "黄色",
      "first_seen_at": "2026-07-14T21:09:32",
      "last_seen_at": "2026-07-14T21:09:32",
      "consecutive_count": 1,
      "peak_rank": 5,
      "is_new": true
    },
    {
      "title": "广东省梅州市丰顺县气象台发布雷雨黄色预警信号",
      "url": "http://www.weather.com.cn/alarm/newalarmcontent.shtml?file=101280406-20260714133500-9302.html",
      "last_hot_value": "黄色",
      "first_seen_at": "2026-07-14T05:57:24",
      "last_seen_at": "2026-07-14T05:57:24",
      "consecutive_count": 0,
      "peak_rank": 5,
      "is_new": false
    },
    {
      "title": "山西省吕梁市中阳县气象台发布暴雨蓝色预警信号",
      "url": "https://www.nmc.cn/publish/alarm/14112941600000_20260714110700.html",
      "last_hot_value": "蓝色",
      "first_seen_at": "2026-07-14T03:32:11",
      "last_seen_at": "2026-07-14T03:32:11",
      "consecutive_count": 0,
      "peak_rank": 5,
      "is_new": false
    },
    {
      "title": "宁夏回族自治区吴忠市盐池县气象台发布暴雨黄色预警信号",
      "url": "https://www.nmc.cn/publish/alarm/64032341600000_20260714051634.html",
      "last_hot_value": "黄色",
      "first_seen_at": "2026-07-13T21:42:20",
      "last_seen_at": "2026-07-13T21:42:20",
      "consecutive_count": 0,
      "peak_rank": 5,
      "is_new": false
    },
    {
      "title": "辽宁省大连市普兰店区气象台发布暴雨橙色预警信号",
      "url": "https://www.nmc.cn/publish/alarm/21021441600000_20260714040500.html",
      "last_hot_value": "橙色",
      "first_seen_at": "2026-07-13T20:30:52",
      "last_seen_at": "2026-07-13T20:30:52",
      "consecutive_count": 0,
      "peak_rank": 5,
      "is_new": false
    },
    {
      "title": "江西省赣州市安远县气象台发布雷电黄色预警信号",
      "url": "https://www.nmc.cn/publish/alarm/36072641600000_20260713044600.html",
      "last_hot_value": "黄色",
      "first_seen_at": "2026-07-12T21:19:19",
      "last_seen_at": "2026-07-12T21:19:19",
      "consecutive_count": 0,
      "peak_rank": 5,
      "is_new": false
    },
    {
      "title": "浙江省台州市临海市气象台发布大风黄色预警信号",
      "url": "https://www.nmc.cn/publish/alarm/33108241600000_20260712191607.html",
      "last_hot_value": "黄色",
      "first_seen_at": "2026-07-12T11:55:11",
      "last_seen_at": "2026-07-12T11:55:11",
      "consecutive_count": 0,
      "peak_rank": 5,
      "is_new": false
    },
    {
      "title": "黑龙江省佳木斯市气象台发布大雾橙色预警信号",
      "url": "https://www.nmc.cn/publish/alarm/23080041600000_20260715041607.html",
      "last_hot_value": "橙色",
      "first_seen_at": "2026-07-14T21:09:32",
      "last_seen_at": "2026-07-14T21:09:32",
      "consecutive_count": 1,
      "peak_rank": 6,
      "is_new": true
    },
    {
      "title": "山西省吕梁市汾阳市气象台发布暴雨蓝色预警信号",
      "url": "http://www.weather.com.cn/alarm/newalarmcontent.shtml?file=101101111-20260714133500-0201.html",
      "last_hot_value": "蓝色",
      "first_seen_at": "2026-07-14T05:57:24",
      "last_seen_at": "2026-07-14T05:57:24",
      "consecutive_count": 0,
      "peak_rank": 6,
      "is_new": false
    },
    {
      "title": "广西壮族自治区柳州市融安县气象台发布高温橙色预警信号",
      "url": "https://www.nmc.cn/publish/alarm/45022441600000_20260714110643.html",
      "last_hot_value": "橙色",
      "first_seen_at": "2026-07-14T03:32:11",
      "last_seen_at": "2026-07-14T03:32:11",
      "consecutive_count": 0,
      "peak_rank": 6,
      "is_new": false
    },
    {
      "title": "辽宁省本溪市本溪满族自治县气象台发布暴雨橙色预警信号",
      "url": "https://www.nmc.cn/publish/alarm/21052141600000_20260714051300.html",
      "last_hot_value": "橙色",
      "first_seen_at": "2026-07-13T21:42:20",
      "last_seen_at": "2026-07-13T21:42:20",
      "consecutive_count": 0,
      "peak_rank": 6,
      "is_new": false
    },
    {
      "title": "安徽省六安市霍邱县气象台发布大雾黄色预警信号",
      "url": "https://www.nmc.cn/publish/alarm/34152241600000_20260714035919.html",
      "last_hot_value": "黄色",
      "first_seen_at": "2026-07-13T20:30:52",
      "last_seen_at": "2026-07-13T20:30:52",
      "consecutive_count": 0,
      "peak_rank": 6,
      "is_new": false
    },
    {
      "title": "江西省赣州市会昌县气象台发布暴雨橙色预警信号",
      "url": "https://www.nmc.cn/publish/alarm/36073341600000_20260713044559.html",
      "last_hot_value": "橙色",
      "first_seen_at": "2026-07-12T21:19:19",
      "last_seen_at": "2026-07-12T21:19:19",
      "consecutive_count": 0,
      "peak_rank": 6,
      "is_new": false
    },
    {
      "title": "山西省临汾市乡宁县自然资源局和乡宁县气象台发布地质灾害蓝色预警信号",
      "url": "https://www.nmc.cn/publish/alarm/14102941600000_20260712191605.html",
      "last_hot_value": "蓝色",
      "first_seen_at": "2026-07-12T11:55:11",
      "last_seen_at": "2026-07-12T11:55:11",
      "consecutive_count": 0,
      "peak_rank": 6,
      "is_new": false
    },
    {
      "title": "广西壮族自治区来宾市金秀县气象台发布雷电黄色预警信号",
      "url": "https://www.nmc.cn/publish/alarm/45132441600000_20260715041509.html",
      "last_hot_value": "黄色",
      "first_seen_at": "2026-07-14T21:09:32",
      "last_seen_at": "2026-07-14T21:09:32",
      "consecutive_count": 1,
      "peak_rank": 7,
      "is_new": true
    },
    {
      "title": "吉林省通化市梅河口市气象台发布暴雨橙色预警信号",
      "url": "http://www.weather.com.cn/alarm/newalarmcontent.shtml?file=101060502-20260714133347-0203.html",
      "last_hot_value": "橙色",
      "first_seen_at": "2026-07-14T05:57:24",
      "last_seen_at": "2026-07-14T05:57:24",
      "consecutive_count": 0,
      "peak_rank": 7,
      "is_new": false
    },
    {
      "title": "重庆市大足区气象台发布高温红色预警信号",
      "url": "https://www.nmc.cn/publish/alarm/50011141600000_20260714110451.html",
      "last_hot_value": "红色",
      "first_seen_at": "2026-07-14T03:32:11",
      "last_seen_at": "2026-07-14T03:32:11",
      "consecutive_count": 0,
      "peak_rank": 7,
      "is_new": false
    },
    {
      "title": "辽宁省营口市盖州市气象台发布暴雨橙色预警信号",
      "url": "https://www.nmc.cn/publish/alarm/21088141600000_20260714050600.html",
      "last_hot_value": "橙色",
      "first_seen_at": "2026-07-13T21:42:20",
      "last_seen_at": "2026-07-13T21:42:20",
      "consecutive_count": 0,
      "peak_rank": 7,
      "is_new": false
    },
    {
      "title": "辽宁省大连市庄河市气象台发布暴雨橙色预警信号",
      "url": "https://www.nmc.cn/publish/alarm/21028341600000_20260714035900.html",
      "last_hot_value": "橙色",
      "first_seen_at": "2026-07-13T20:30:52",
      "last_seen_at": "2026-07-13T20:30:52",
      "consecutive_count": 0,
      "peak_rank": 7,
      "is_new": false
    },
    {
      "title": "河北省唐山市滦州市气象台发布暴雨蓝色预警信号",
      "url": "https://www.nmc.cn/publish/alarm/13028441600000_20260713044357.html",
      "last_hot_value": "蓝色",
      "first_seen_at": "2026-07-12T21:19:19",
      "last_seen_at": "2026-07-12T21:19:19",
      "consecutive_count": 0,
      "peak_rank": 7,
      "is_new": false
    },
    {
      "title": "贵州省毕节市金沙县气象台发布雷电黄色预警信号",
      "url": "https://www.nmc.cn/publish/alarm/52052341600000_20260712191555.html",
      "last_hot_value": "黄色",
      "first_seen_at": "2026-07-12T11:55:11",
      "last_seen_at": "2026-07-12T11:55:11",
      "consecutive_count": 0,
      "peak_rank": 7,
      "is_new": false
    },
    {
      "title": "广东省广州市番禺区气象台发布暴雨黄色预警信号",
      "url": "https://www.nmc.cn/publish/alarm/44011341600000_20260715041433.html",
      "last_hot_value": "黄色",
      "first_seen_at": "2026-07-14T21:09:32",
      "last_seen_at": "2026-07-14T21:09:32",
      "consecutive_count": 1,
      "peak_rank": 8,
      "is_new": true
    },
    {
      "title": "陕西省榆林市佳县气象台发布暴雨橙色预警信号",
      "url": "http://www.weather.com.cn/alarm/newalarmcontent.shtml?file=101110404-20260714133330-0203.html",
      "last_hot_value": "橙色",
      "first_seen_at": "2026-07-14T05:57:24",
      "last_seen_at": "2026-07-14T05:57:24",
      "consecutive_count": 0,
      "peak_rank": 8,
      "is_new": false
    },
    {
      "title": "山西省运城市气象台发布暴雨蓝色预警信号",
      "url": "https://www.nmc.cn/publish/alarm/14080041600000_20260714110403.html",
      "last_hot_value": "蓝色",
      "first_seen_at": "2026-07-14T03:32:11",
      "last_seen_at": "2026-07-14T03:32:11",
      "consecutive_count": 0,
      "peak_rank": 8,
      "is_new": false
    },
    {
      "title": "福建省漳州市龙海区气象台发布雷电黄色预警信号",
      "url": "https://www.nmc.cn/publish/alarm/35060441600000_20260714110400.html",
      "last_hot_value": "黄色",
      "first_seen_at": "2026-07-13T21:42:20",
      "last_seen_at": "2026-07-14T03:32:11",
      "consecutive_count": 0,
      "peak_rank": 8,
      "is_new": false
    },
    {
      "title": "广西壮族自治区贵港市气象台发布暴雨橙色预警信号",
      "url": "https://www.nmc.cn/publish/alarm/45080041600000_20260714035802.html",
      "last_hot_value": "橙色",
      "first_seen_at": "2026-07-13T20:30:52",
      "last_seen_at": "2026-07-13T20:30:52",
      "consecutive_count": 0,
      "peak_rank": 8,
      "is_new": false
    },
    {
      "title": "安徽省合肥市庐江县气象台发布暴雨蓝色预警信号",
      "url": "https://www.nmc.cn/publish/alarm/34012441600000_20260713044322.html",
      "last_hot_value": "蓝色",
      "first_seen_at": "2026-07-12T21:19:19",
      "last_seen_at": "2026-07-12T21:19:19",
      "consecutive_count": 0,
      "peak_rank": 8,
      "is_new": false
    },
    {
      "title": "安徽省合肥市长丰县气象台发布台风黄色预警信号",
      "url": "https://www.nmc.cn/publish/alarm/34012141600000_20260712191504.html",
      "last_hot_value": "黄色",
      "first_seen_at": "2026-07-12T11:55:11",
      "last_seen_at": "2026-07-12T11:55:11",
      "consecutive_count": 0,
      "peak_rank": 8,
      "is_new": false
    },
    {
      "title": "黑龙江省佳木斯市桦川县气象台发布大雾橙色预警信号",
      "url": "https://www.nmc.cn/publish/alarm/23082641600000_20260715041336.html",
      "last_hot_value": "橙色",
      "first_seen_at": "2026-07-14T21:09:32",
      "last_seen_at": "2026-07-14T21:09:32",
      "consecutive_count": 1,
      "peak_rank": 9,
      "is_new": true
    },
    {
      "title": "福建省宁德市福安市气象台发布雷电黄色预警信号",
      "url": "http://www.weather.com.cn/alarm/newalarmcontent.shtml?file=101230306-20260714133300-0902.html",
      "last_hot_value": "黄色",
      "first_seen_at": "2026-07-14T05:57:24",
      "last_seen_at": "2026-07-14T05:57:24",
      "consecutive_count": 0,
      "peak_rank": 9,
      "is_new": false
    },
    {
      "title": "辽宁省沈阳市辽中区气象台发布暴雨红色预警信号",
      "url": "https://www.nmc.cn/publish/alarm/21011541600000_20260714045600.html",
      "last_hot_value": "红色",
      "first_seen_at": "2026-07-13T21:42:20",
      "last_seen_at": "2026-07-13T21:42:20",
      "consecutive_count": 0,
      "peak_rank": 9,
      "is_new": false
    },
    {
      "title": "江西省鹰潭市余江区气象台发布大雾橙色预警信号",
      "url": "https://www.nmc.cn/publish/alarm/36060341600000_20260714035552.html",
      "last_hot_value": "橙色",
      "first_seen_at": "2026-07-13T20:30:52",
      "last_seen_at": "2026-07-13T20:30:52",
      "consecutive_count": 0,
      "peak_rank": 9,
      "is_new": false
    },
    {
      "title": "安徽省淮南市寿县气象台发布暴雨蓝色预警信号",
      "url": "https://www.nmc.cn/publish/alarm/34042241600000_20260713044217.html",
      "last_hot_value": "蓝色",
      "first_seen_at": "2026-07-12T21:19:19",
      "last_seen_at": "2026-07-12T21:19:19",
      "consecutive_count": 0,
      "peak_rank": 9,
      "is_new": false
    },
    {
      "title": "贵州省毕节市黔西市气象台发布暴雨黄色预警信号",
      "url": "https://www.nmc.cn/publish/alarm/52058141600000_20260712191430.html",
      "last_hot_value": "黄色",
      "first_seen_at": "2026-07-12T11:55:11",
      "last_seen_at": "2026-07-12T11:55:11",
      "consecutive_count": 0,
      "peak_rank": 9,
      "is_new": false
    },
    {
      "title": "黑龙江省佳木斯市抚远市气象台发布暴雨黄色预警信号",
      "url": "https://www.nmc.cn/publish/alarm/23088341600000_20260715041308.html",
      "last_hot_value": "黄色",
      "first_seen_at": "2026-07-14T21:09:32",
      "last_seen_at": "2026-07-14T21:09:32",
      "consecutive_count": 1,
      "peak_rank": 10,
      "is_new": true
    },
    {
      "title": "陕西省榆林市吴堡县气象台发布暴雨橙色预警信号",
      "url": "http://www.weather.com.cn/alarm/newalarmcontent.shtml?file=101110411-20260714133229-0203.html",
      "last_hot_value": "橙色",
      "first_seen_at": "2026-07-14T05:57:24",
      "last_seen_at": "2026-07-14T05:57:24",
      "consecutive_count": 0,
      "peak_rank": 10,
      "is_new": false
    },
    {
      "title": "内蒙古自治区呼伦贝尔市满洲里市气象台发布大风蓝色预警信号",
      "url": "https://www.nmc.cn/publish/alarm/15078141600000_20260714110344.html",
      "last_hot_value": "蓝色",
      "first_seen_at": "2026-07-14T03:32:11",
      "last_seen_at": "2026-07-14T03:32:11",
      "consecutive_count": 0,
      "peak_rank": 10,
      "is_new": false
    },
    {
      "title": "辽宁省本溪市气象台发布暴雨橙色预警信号",
      "url": "https://www.nmc.cn/publish/alarm/21050041600000_20260714045500.html",
      "last_hot_value": "橙色",
      "first_seen_at": "2026-07-13T21:42:20",
      "last_seen_at": "2026-07-13T21:42:20",
      "consecutive_count": 0,
      "peak_rank": 10,
      "is_new": false
    },
    {
      "title": "广东省江门市新会区气象台发布暴雨黄色预警信号",
      "url": "https://www.nmc.cn/publish/alarm/44070541600000_20260714035445.html",
      "last_hot_value": "黄色",
      "first_seen_at": "2026-07-13T20:30:52",
      "last_seen_at": "2026-07-13T20:30:52",
      "consecutive_count": 0,
      "peak_rank": 10,
      "is_new": false
    },
    {
      "title": "辽宁省葫芦岛市气象台发布暴雨橙色预警信号",
      "url": "https://www.nmc.cn/publish/alarm/21140041600000_20260713043900.html",
      "last_hot_value": "橙色",
      "first_seen_at": "2026-07-12T21:19:19",
      "last_seen_at": "2026-07-12T21:19:19",
      "consecutive_count": 0,
      "peak_rank": 10,
      "is_new": false
    },
    {
      "title": "云南省大理白族自治州南涧彝族自治县气象台发布雷电黄色预警信号",
      "url": "https://www.nmc.cn/publish/alarm/53292641600000_20260712191419.html",
      "last_hot_value": "黄色",
      "first_seen_at": "2026-07-12T11:55:11",
      "last_seen_at": "2026-07-12T11:55:11",
      "consecutive_count": 0,
      "peak_rank": 10,
      "is_new": false
    }
  ]
}